{"match_id": "NRL20241604", "team_A": {"id": 55017, "name": "South Sydney", "code": "SOU", "stats": {"challenges": 1, "decoys": 42, "errors": 12, "forties": 0, "inCompleteSets": 9, "kicks": 25, "momentum": null, "options": 46, "penaltiesAwarded": 10, "period": null, "points": 14, "runs": 194, "tackledOpp20": 33, "tackles": 317, "territory": 43.54, "tries": 3, "supports": 4, "attacking_kicks": 9, "correct_challenges": 0, "incorrect_challenges": 1, "challenge_percentage": 0.0, "complete_sets": 38, "completion_rate": "38/47", "drop_outs": 0, "dummy_half_runs": 10, "effective_offloads": 8, "field_goal_attempts": 0, "field_goal_misses": 0, "field_goals": 0, "forced_drop_outs": 2, "general_play_pass": 95, "goal_percentage": 33.3, "goal_rate": "1 from 3", "in_goal_escapes": 0, "interchanges_off": 0, "interchanges_on": 0, "kick_metres": 665, "kicks_2040": 0, "kicks_4020": 0, "kicks_dead": 2, "last_touch_try_assists": 0, "line_break_assists": 4, "line_break_causes": 2, "line_breaks": 4, "line_engagements": 37, "long_kicks": 11, "missed_tackles": 27, "off_loads": 9, "one_pass_runs": 103, "penalties_conceded": 3, "play_the_balls": 176, "possession_last10": 51, "possession_percentage": 53, "possession_time": 1762012, "run_metres": 1641, "runs_7less_meters": 76, "runs_8plus_meters": 118, "send_offs": 0, "sin_bins": 0, "steals_one_on_one": 0, "stolen_one_on_one": 0, "tackle_busts": 35, "tackle_opp_half": 79, "tackles_one_on_one": 28, "territory_time": 1442646, "total_sets": 47, "try_assists": 3, "try_causes": 0, "try_contributions": 0, "try_involvements": 6, "twenty_metre_restarts": 1, "two_point_field_goals": 0, "two_point_field_goal_misses": 0, "weighted_kicks": 5, "win_prediction_percentage": 100.0, "post_contact_metres": 560, "set_restart_infringements_conceded": 3, "set_restart_infringements_awarded": 3}, "short_name": "Rabbitohs"}, "team_B": {"id": 55009, "name": "Manly", "code": "MAN", "stats": {"challenges": 1, "decoys": 37, "errors": 13, "forties": 0, "inCompleteSets": 12, "kicks": 20, "momentum": null, "options": 41, "penaltiesAwarded": 3, "period": null, "points": 0, "runs": 164, "tackledOpp20": 29, "tackles": 383, "territory": 56.46, "tries": 0, "supports": 4, "attacking_kicks": 10, "correct_challenges": 0, "incorrect_challenges": 1, "challenge_percentage": 0.0, "complete_sets": 27, "completion_rate": "27/39", "drop_outs": 2, "dummy_half_runs": 5, "effective_offloads": 6, "field_goal_attempts": 0, "field_goal_misses": 0, "field_goals": 0, "forced_drop_outs": 0, "general_play_pass": 99, "goal_percentage": 0.0, "goal_rate": "0 from 0", "in_goal_escapes": 0, "interchanges_off": 0, "interchanges_on": 0, "kick_metres": 510, "kicks_2040": 0, "kicks_4020": 0, "kicks_dead": 1, "last_touch_try_assists": 0, "line_break_assists": 1, "line_break_causes": 4, "line_breaks": 1, "line_engagements": 32, "long_kicks": 9, "missed_tackles": 35, "off_loads": 8, "one_pass_runs": 81, "penalties_conceded": 10, "play_the_balls": 158, "possession_last10": 49, "possession_percentage": 47, "possession_time": 1551566, "run_metres": 1553, "runs_7less_meters": 55, "runs_8plus_meters": 109, "send_offs": 0, "sin_bins": 0, "steals_one_on_one": 0, "stolen_one_on_one": 0, "tackle_busts": 27, "tackle_opp_half": 74, "tackles_one_on_one": 28, "territory_time": 1870932, "total_sets": 39, "try_assists": 0, "try_causes": 3, "try_contributions": 0, "try_involvements": 0, "twenty_metre_restarts": 2, "two_point_field_goals": 0, "two_point_field_goal_misses": 0, "weighted_kicks": 1, "win_prediction_percentage": 0.0, "post_contact_metres": 538, "set_restart_infringements_conceded": 3, "set_restart_infringements_awarded": 3}, "short_name": "Sea Eagles"}}