{"match_id": "NRL20240303", "team_A": {"id": 55013, "name": "Sydney Roosters", "code": "SYD", "stats": {"challenges": 1, "decoys": 19, "errors": 8, "forties": 0, "inCompleteSets": 6, "kicks": 28, "momentum": null, "options": 39, "penaltiesAwarded": 5, "period": null, "points": 48, "runs": 165, "tackledOpp20": 18, "tackles": 283, "territory": 52.55, "tries": 8, "supports": 20, "attacking_kicks": 11, "correct_challenges": 1, "incorrect_challenges": 0, "challenge_percentage": 1.0, "complete_sets": 37, "completion_rate": "37/43", "drop_outs": 1, "dummy_half_runs": 10, "effective_offloads": 6, "field_goal_attempts": 0, "field_goal_misses": 0, "field_goals": 0, "forced_drop_outs": 2, "general_play_pass": 98, "goal_percentage": 100.0, "goal_rate": "8 from 8", "in_goal_escapes": 0, "interchanges_off": 0, "interchanges_on": 0, "kick_metres": 728, "kicks_2040": 0, "kicks_4020": 0, "kicks_dead": 1, "last_touch_try_assists": 0, "line_break_assists": 8, "line_break_causes": 6, "line_breaks": 8, "line_engagements": 31, "long_kicks": 15, "missed_tackles": 35, "off_loads": 10, "one_pass_runs": 74, "penalties_conceded": 5, "play_the_balls": 142, "possession_last10": 49, "possession_percentage": 52, "possession_time": 1490950, "run_metres": 1501, "runs_7less_meters": 53, "runs_8plus_meters": 112, "send_offs": 0, "sin_bins": 0, "steals_one_on_one": 2, "stolen_one_on_one": 1, "tackle_busts": 38, "tackle_opp_half": 61, "tackles_one_on_one": 24, "territory_time": 1498726, "total_sets": 43, "try_assists": 7, "try_causes": 2, "try_contributions": 7, "try_involvements": 22, "twenty_metre_restarts": 2, "two_point_field_goals": 0, "two_point_field_goal_misses": 0, "weighted_kicks": 0, "win_prediction_percentage": 100.0, "post_contact_metres": 469, "set_restart_infringements_conceded": 5, "set_restart_infringements_awarded": 1}, "short_name": "Roosters"}, "team_B": {"id": 55017, "name": "South Sydney", "code": "SOU", "stats": {"challenges": 0, "decoys": 37, "errors": 14, "forties": 0, "inCompleteSets": 12, "kicks": 18, "momentum": null, "options": 46, "penaltiesAwarded": 5, "period": null, "points": 6, "runs": 150, "tackledOpp20": 30, "tackles": 309, "territory": 47.45, "tries": 1, "supports": 9, "attacking_kicks": 8, "correct_challenges": 0, "incorrect_challenges": 0, "challenge_percentage": 0.0, "complete_sets": 27, "completion_rate": "27/39", "drop_outs": 2, "dummy_half_runs": 6, "effective_offloads": 6, "field_goal_attempts": 0, "field_goal_misses": 0, "field_goals": 0, "forced_drop_outs": 1, "general_play_pass": 98, "goal_percentage": 100.0, "goal_rate": "1 from 1", "in_goal_escapes": 0, "interchanges_off": 0, "interchanges_on": 0, "kick_metres": 410, "kicks_2040": 0, "kicks_4020": 0, "kicks_dead": 0, "last_touch_try_assists": 0, "line_break_assists": 3, "line_break_causes": 12, "line_breaks": 4, "line_engagements": 51, "long_kicks": 9, "missed_tackles": 38, "off_loads": 7, "one_pass_runs": 67, "penalties_conceded": 5, "play_the_balls": 135, "possession_last10": 51, "possession_percentage": 48, "possession_time": 1361038, "run_metres": 1276, "runs_7less_meters": 64, "runs_8plus_meters": 86, "send_offs": 0, "sin_bins": 1, "steals_one_on_one": 1, "stolen_one_on_one": 2, "tackle_busts": 35, "tackle_opp_half": 56, "tackles_one_on_one": 27, "territory_time": 1353262, "total_sets": 39, "try_assists": 1, "try_causes": 14, "try_contributions": 0, "try_involvements": 2, "twenty_metre_restarts": 1, "two_point_field_goals": 0, "two_point_field_goal_misses": 0, "weighted_kicks": 1, "win_prediction_percentage": 0.0, "post_contact_metres": 426, "set_restart_infringements_conceded": 1, "set_restart_infringements_awarded": 5}, "short_name": "Rabbitohs"}}