{"match_id": "NRL20231703", "team_A": {"id": 55011, "name": "Penrith", "code": "PEN", "stats": {"challenges": 0, "decoys": 40, "errors": 4, "forties": 0, "inCompleteSets": 3, "kicks": 30, "momentum": null, "options": 60, "penaltiesAwarded": 6, "period": null, "points": 20, "runs": 200, "tackledOpp20": 50, "tackles": 290, "territory": 67.3, "tries": 4, "supports": 20, "attacking_kicks": 19, "correct_challenges": 0, "incorrect_challenges": 0, "challenge_percentage": 0.0, "complete_sets": 39, "completion_rate": "39/42", "drop_outs": 0, "dummy_half_runs": 10, "effective_offloads": 10, "field_goal_attempts": 0, "field_goal_misses": 0, "field_goals": 0, "forced_drop_outs": 3, "general_play_pass": 152, "goal_percentage": 50.0, "goal_rate": "2 from 4", "in_goal_escapes": 1, "interchanges_off": 0, "interchanges_on": 0, "kick_metres": 666, "kicks_2040": 0, "kicks_4020": 0, "kicks_dead": 2, "last_touch_try_assists": 0, "line_break_assists": 2, "line_break_causes": 8, "line_breaks": 4, "line_engagements": 37, "long_kicks": 10, "missed_tackles": 33, "off_loads": 11, "one_pass_runs": 89, "penalties_conceded": 2, "play_the_balls": 182, "possession_last10": 56, "possession_percentage": 57, "possession_time": 1841470, "run_metres": 1731, "runs_7less_meters": 74, "runs_8plus_meters": 126, "send_offs": 0, "sin_bins": 0, "steals_one_on_one": 1, "stolen_one_on_one": 0, "tackle_busts": 49, "tackle_opp_half": 99, "tackles_one_on_one": 26, "territory_time": 2157633, "total_sets": 42, "try_assists": 2, "try_causes": 3, "try_contributions": 3, "try_involvements": 9, "twenty_metre_restarts": 0, "two_point_field_goals": 0, "two_point_field_goal_misses": 0, "weighted_kicks": 1, "win_prediction_percentage": 100.0, "post_contact_metres": 588, "set_restart_infringements_conceded": 2, "set_restart_infringements_awarded": 2}, "short_name": "Panthers"}, "team_B": {"id": 55007, "name": "Newcastle", "code": "NEW", "stats": {"challenges": 0, "decoys": 41, "errors": 12, "forties": 0, "inCompleteSets": 10, "kicks": 20, "momentum": null, "options": 54, "penaltiesAwarded": 2, "period": null, "points": 12, "runs": 154, "tackledOpp20": 4, "tackles": 375, "territory": 32.7, "tries": 2, "supports": 13, "attacking_kicks": 4, "correct_challenges": 0, "incorrect_challenges": 0, "challenge_percentage": 0.0, "complete_sets": 23, "completion_rate": "23/33", "drop_outs": 3, "dummy_half_runs": 6, "effective_offloads": 7, "field_goal_attempts": 0, "field_goal_misses": 0, "field_goals": 0, "forced_drop_outs": 0, "general_play_pass": 116, "goal_percentage": 100.0, "goal_rate": "2 from 2", "in_goal_escapes": 1, "interchanges_off": 0, "interchanges_on": 0, "kick_metres": 589, "kicks_2040": 0, "kicks_4020": 0, "kicks_dead": 0, "last_touch_try_assists": 0, "line_break_assists": 3, "line_break_causes": 6, "line_breaks": 5, "line_engagements": 39, "long_kicks": 13, "missed_tackles": 49, "off_loads": 12, "one_pass_runs": 72, "penalties_conceded": 6, "play_the_balls": 143, "possession_last10": 44, "possession_percentage": 43, "possession_time": 1364753, "run_metres": 1258, "runs_7less_meters": 66, "runs_8plus_meters": 88, "send_offs": 0, "sin_bins": 1, "steals_one_on_one": 0, "stolen_one_on_one": 1, "tackle_busts": 33, "tackle_opp_half": 34, "tackles_one_on_one": 28, "territory_time": 1048590, "total_sets": 33, "try_assists": 1, "try_causes": 7, "try_contributions": 1, "try_involvements": 4, "twenty_metre_restarts": 3, "two_point_field_goals": 0, "two_point_field_goal_misses": 0, "weighted_kicks": 3, "win_prediction_percentage": 0.0, "post_contact_metres": 416, "set_restart_infringements_conceded": 2, "set_restart_infringements_awarded": 2}, "short_name": "Knights"}}